missinglink/__init__.py
missinglink/resource_manager/__init__.py
missinglink/resource_manager/docker/__init__.py
missinglink/resource_manager/docker/cli.py
missinglink/resource_manager/docker/utils.py
missinglink/resource_manager/docker/app/__init__.py
missinglink/resource_manager/docker/app/app.py
missinglink/resource_manager/docker/config/__init__.py
missinglink/resource_manager/docker/config/config_builder.py
missinglink/resource_manager/docker/config/configuration.py
missinglink/resource_manager/docker/config/configuration_instance.py
missinglink/resource_manager/docker/config/windows_configuration_instance.py
missinglink/resource_manager/docker/controllers/__init__.py
missinglink/resource_manager/docker/controllers/cloud_logger.py
missinglink/resource_manager/docker/controllers/crypto_helper.py
missinglink/resource_manager/docker/controllers/errors.py
missinglink/resource_manager/docker/controllers/invocation_docker.py
missinglink/resource_manager/docker/controllers/windows_invocation_docker.py
missinglink/resource_manager/docker/controllers/aws/__init__.py
missinglink/resource_manager/docker/controllers/aws/ecr.py
missinglink/resource_manager/docker/controllers/docker/__init__.py
missinglink/resource_manager/docker/controllers/docker/async_docker_container.py
missinglink/resource_manager/docker/controllers/docker/docker_wrapper.py
missinglink/resource_manager/docker/controllers/docker/log_generator.py
missinglink/resource_manager/docker/controllers/docker/stat_generator.py
missinglink/resource_manager/docker/controllers/docker/spot_instance_monitor/__init__.py
missinglink/resource_manager/docker/controllers/docker/spot_instance_monitor/aws_spot_instance_monitor.py
missinglink/resource_manager/docker/controllers/docker/spot_instance_monitor/spot_instance_monitor.py
missinglink/resource_manager/docker/controllers/gcp/__init__.py
missinglink/resource_manager/docker/controllers/gcp/gcr.py
missinglink/resource_manager/docker/controllers/templates/__init__.py
missinglinkai_resource_manager_docker-19.9.2606.dist-info/METADATA
missinglinkai_resource_manager_docker-19.9.2606.dist-info/WHEEL
missinglinkai_resource_manager_docker-19.9.2606.dist-info/dependency_links.txt
missinglinkai_resource_manager_docker-19.9.2606.dist-info/entry_points.txt
missinglinkai_resource_manager_docker-19.9.2606.dist-info/top_level.txt
missinglinkai_resource_manager_docker-19.9.2606.dist-info/RECORD
