Metadata-Version: 2.1
Name: missinglinkai-resource-manager-docker
Version: 19.9.2606
Summary: MissingLink.ai Resource Manager - Docker version
Home-page: https://missinglink.ai
Author: MissingLink
Author-email: support+rmdocker@missinglink.ai
License: UNKNOWN
Keywords: missinglink missinglinkai
Platform: UNKNOWN
Classifier: Development Status :: 4 - Beta
Classifier: Intended Audience :: Science/Research
Classifier: License :: Other/Proprietary License
Classifier: Topic :: Software Development :: Build Tools
Classifier: Programming Language :: Python :: 3.6
Requires-Python: ~=3.6
Requires-Dist: docker (~=3.6)
Requires-Dist: PyYaml (~=3.13)
Requires-Dist: python-dateutil
Requires-Dist: websockets (~=7.0)
Requires-Dist: PyJWT (~=1.6.4)
Requires-Dist: gitpython (~=2.1)
Requires-Dist: click (~=6.7)
Requires-Dist: ml-crypto[pycryptodomex] (~=0.7.811)
Requires-Dist: autobahn (~=17.10)
Requires-Dist: async-generator (~=1.9)
Requires-Dist: boto3 (~=1.7)
Requires-Dist: six (~=1.11.0)
Requires-Dist: aiohttp (~=3.3)
Requires-Dist: Jinja2 (~=2.10)
Requires-Dist: sentry-sdk (~=0.10)
Requires-Dist: netifaces (~=0.10.9)
Requires-Dist: ml-legit (>=19.9.8411)
Requires-Dist: requests (~=2.20)
Requires-Dist: google-cloud-logging (~=1.12.0)
